[{
    "id":1,
    "name":"ABC",
    "title":"Lorem ipsum dolor sit amet consectetur adipisicing elit.",
    "price":0,
    "category":"free",
    "image":"./Banner.jpg"
},{
    "id":2,
    "name":"ABC",
    "title":"Lorem ipsum dolor sit amet consectetur adipisicing elit.",
    "price":0,
    "category":"",
    "image":"./Banner.jpg"
},
{
    "id":3,
    "name":"ABC",
    "title":"Lorem ipsum dolor sit amet consectetur adipisicing elit.",
    "price":0,
    "category":"",
    "image":"./Banner.jpg"
},{
    "id":4,
    "name":"ABC",
    "title":"Lorem ipsum dolor sit amet consectetur adipisicing elit.",
    "price":0,
    "category":"free",
    "image":"./Banner.jpg"
},{
    "id":5,
    "name":"ABC",
    "title":"Lorem ipsum dolor sit amet consectetur adipisicing elit.",
    "price":0,
    "category":"free",
    "image":"./Banner.jpg"
},{
    "id":6,
    "name":"ABC",
    "title":"Lorem ipsum dolor sit amet consectetur adipisicing elit.",
    "price":0,
    "category":"free",
    "image":"./Banner.jpg"
},{
    "id":7,
    "name":"ABC",
    "title":"Lorem ipsum dolor sit amet consectetur adipisicing elit.",
    "price":0,
    "category":"",
    "image":"./Banner.jpg"
},{
    "id":8,
    "name":"ABC",
    "title":"Lorem ipsum dolor sit amet consectetur adipisicing elit.",
    "price":0,
    "category":"free",
    "image":"./Banner.jpg"
},{
    "id":9,
    "name":"ABC",
    "title":"Lorem ipsum dolor sit amet consectetur adipisicing elit.",
    "price":0,
    "category":"free",
    "image":"./Banner.jpg"
},{
    "id":10,
    "name":"ABC",
    "title":"Lorem ipsum dolor sit amet consectetur adipisicing elit.",
    "price":0,
    "category":"",
    "image":"./Banner.jpg"
}]